LICENSE
README.rst
setup.py
tof_gtk.desktop
scripts/tof_gtk
tof_simulator.egg-info/PKG-INFO
tof_simulator.egg-info/SOURCES.txt
tof_simulator.egg-info/dependency_links.txt
tof_simulator.egg-info/top_level.txt
tofsim/__init__.py
tofsim/nist_data.txt
tofsim/nist_elem.py
tofsim/tof.conf
tofsim/tof.py
tofsim/tof_gtk.py
tofsim/tof_gtk.ui
tofsim/tof_teoria.pdf
tofsim/version.py