Metadata-Version: 2.1
Name: tof-simulator
Version: 3.5
Summary: Time-of-Flight Mass spectrometry simulator
Home-page: https://github.com/fiolj/tof-simulator
Author: Juan Fiol
Author-email: juanfiol@gmail.com
Keywords: simulation,mass-spectrometry,TOF
Classifier: Programming Language :: Python :: 3
Classifier: Operating System :: OS Independent
License-File: LICENSE
